ucroe/__init__.py
ucroe/cache_backend/__init__.py
ucroe/cache_backend/abc.py
ucroe/cache_backend/cachetools.py
ucroe/cache_backend/django.py
ucroe/config.py
ucroe/decorators.py
ucroe/exceptions.py
ucroe-0.1.0.dist-info/LICENSE
ucroe-0.1.0.dist-info/METADATA
ucroe-0.1.0.dist-info/WHEEL
ucroe-0.1.0.dist-info/RECORD
