Metadata-Version: 2.1
Name: ucroe
Version: 0.1.0
Summary: a Python decorator that caches a function’s return value and reuses it if the function raises an exception on subsequent calls
License: MIT
Author: Melvin Koh
Author-email: melvinkcx@gmail.com
Requires-Python: >=3.10,<4.0
Classifier: Framework :: Django
Classifier: License :: OSI Approved :: MIT License
Classifier: Programming Language :: Python :: 3
Classifier: Programming Language :: Python :: 3.10
Classifier: Programming Language :: Python :: 3.11
Classifier: Programming Language :: Python :: 3.12
Classifier: Programming Language :: Python :: 3.13
Classifier: Topic :: Software Development :: Libraries
Classifier: Topic :: Utilities
Requires-Dist: cachetools (>=5.0.0,<6.0.0)
Requires-Dist: typing-extensions (>=4.1,<5.0) ; python_full_version <= "3.10.0"
